mcp_server_voicevox/README.md
mcp_server_voicevox/__init__.py
mcp_server_voicevox/__main__.py
mcp_server_voicevox/server.py
mcp_server_voicevox-0.2.0.dist-info/METADATA
mcp_server_voicevox-0.2.0.dist-info/WHEEL
mcp_server_voicevox-0.2.0.dist-info/entry_points.txt
mcp_server_voicevox-0.2.0.dist-info/RECORD
