Metadata-Version: 2.4
Name: mcp-server-voicevox
Version: 0.2.0
Summary: A Model Context Protocol server providing VoiceVox text-to-speech functionality for LLMs
Project-URL: Repository, https://github.com/Sunwood-ai-labs/mcp-voicevox
Project-URL: PyPI, https://pypi.org/project/mcp-server-voicevox/
Author-email: VoiceVox MCP Developer <example@example.com>
License: MIT
Keywords: llm,mcp,text-to-speech,tts,voicevox
Classifier: Development Status :: 4 - Beta
Classifier: Intended Audience :: Developers
Classifier: License :: OSI Approved :: MIT License
Classifier: Programming Language :: Python :: 3
Classifier: Programming Language :: Python :: 3.10
Requires-Python: >=3.10
Requires-Dist: mcp>=1.0.0
Requires-Dist: pydantic>=2.0.0
Requires-Dist: requests>=2.31.0
